django_sso_bridge/__init__.py
django_sso_bridge/access_token_response.py
django_sso_bridge/auth_sso.py
django_sso_bridge/auth_user.py
django_sso_bridge-0.1.0.dist-info/LICENSE
django_sso_bridge-0.1.0.dist-info/METADATA
django_sso_bridge-0.1.0.dist-info/WHEEL
django_sso_bridge-0.1.0.dist-info/top_level.txt
django_sso_bridge-0.1.0.dist-info/RECORD
